{
	"modules": [{
		"id": "4ae51d1b-ed81-44db-b398-45f57f88144e",
		"type": "Disconnect",
		"branches": [],
		"parameters": [],
		"metadata": {
			"position": {
				"x": 1571,
				"y": 87
			}
		}
	}, {
		"id": "38550773-620f-4cc8-b6aa-e2ff8e4c3e0e",
		"type": "Transfer",
		"branches": [{
			"condition": "Error",
			"transition": "4ae51d1b-ed81-44db-b398-45f57f88144e"
		}],
		"parameters": [{
			"name": "ContactFlowId",
			"value": "arn:aws:connect:eu-central-1:746022503515:instance/736d65e0-6ce5-4210-9d44-55c366ea9a16/contact-flow/3f4c2b47-2efc-475e-b4d8-16929f8a6c5c",
			"resourceName": "BMWContactFlowInboundCallsNew"
		}],
		"metadata": {
			"position": {
				"x": 1333,
				"y": 48
			},
			"useDynamic": false,
			"ContactFlow": {
				"id": "arn:aws:connect:eu-central-1:746022503515:instance/736d65e0-6ce5-4210-9d44-55c366ea9a16/contact-flow/3f4c2b47-2efc-475e-b4d8-16929f8a6c5c",
				"text": "BMWContactFlowInboundCallsNew"
			}
		},
		"target": "Flow"
	}, {
		"id": "12f8348e-9f93-4523-8d5b-c1dd1cbfc2ba",
		"type": "PlayPrompt",
		"branches": [{
			"condition": "Success",
			"transition": "38550773-620f-4cc8-b6aa-e2ff8e4c3e0e"
		}],
		"parameters": [{
			"name": "Text",
			"value": "After this call the status of the incident will be updated to pending.",
			"namespace": null
		}, {
			"name": "TextToSpeechType",
			"value": "text"
		}],
		"metadata": {
			"position": {
				"x": 1034,
				"y": 2
			},
			"useDynamic": false
		}
	}, {
		"id": "60f8e224-590b-4bb4-a7f2-6f48e8759376",
		"type": "PlayPrompt",
		"branches": [{
			"condition": "Success",
			"transition": "38550773-620f-4cc8-b6aa-e2ff8e4c3e0e"
		}],
		"parameters": [{
			"name": "Text",
			"value": "The status of the incident will remain open.",
			"namespace": null
		}, {
			"name": "TextToSpeechType",
			"value": "text"
		}],
		"metadata": {
			"position": {
				"x": 1037,
				"y": 177
			},
			"useDynamic": false
		}
	}, {
		"id": "1b9f71dd-c18c-44c2-b772-36bbec4d7ec5",
		"type": "SetVoice",
		"branches": [{
			"condition": "Success",
			"transition": "3d30d205-840d-4da2-b5a6-9fbe322de4bb"
		}],
		"parameters": [{
			"name": "GlobalVoice",
			"value": "Brian"
		}],
		"metadata": {
			"position": {
				"x": 192,
				"y": 14
			}
		}
	}, {
		"id": "3d30d205-840d-4da2-b5a6-9fbe322de4bb",
		"type": "PlayPrompt",
		"branches": [{
			"condition": "Success",
			"transition": "7ef514f5-4447-4774-8432-446ad585c631"
		}],
		"parameters": [{
			"name": "Text",
			"value": "Hi. This is an Automated call from BMW incident management services.",
			"namespace": null
		}, {
			"name": "TextToSpeechType",
			"value": "text"
		}],
		"metadata": {
			"position": {
				"x": 247,
				"y": 241
			},
			"useDynamic": false
		}
	}, {
		"id": "35d29379-032f-47a1-bf95-f177ea3fd206",
		"type": "InvokeExternalResource",
		"branches": [{
			"condition": "Success",
			"transition": "12f8348e-9f93-4523-8d5b-c1dd1cbfc2ba"
		}, {
			"condition": "Error",
			"transition": "60f8e224-590b-4bb4-a7f2-6f48e8759376"
		}],
		"parameters": [{
			"name": "FunctionArn",
			"value": "arn:aws:lambda:eu-central-1:746022503515:function:Update_Incident_Status_AWSconnect"
		}, {
			"name": "TimeLimit",
			"value": "3"
		}],
		"metadata": {
			"position": {
				"x": 777,
				"y": 15
			},
			"dynamicMetadata": {}
		},
		"target": "Lambda"
	}, {
		"id": "7ef514f5-4447-4774-8432-446ad585c631",
		"type": "GetUserInput",
		"branches": [{
			"condition": "Timeout",
			"transition": "a2ae63b0-e383-4a6f-a1af-21ab73cb9aa8"
		}, {
			"condition": "NoMatch",
			"transition": "a2ae63b0-e383-4a6f-a1af-21ab73cb9aa8"
		}, {
			"condition": "Error",
			"transition": "a2ae63b0-e383-4a6f-a1af-21ab73cb9aa8"
		}, {
			"condition": "Evaluate",
			"conditionType": "Equals",
			"conditionValue": "0",
			"transition": "fd8d47b5-4188-4e4f-91e9-411aff7cc516"
		}, {
			"condition": "Evaluate",
			"conditionType": "Equals",
			"conditionValue": "1",
			"transition": "fd8d47b5-4188-4e4f-91e9-411aff7cc516"
		}, {
			"condition": "Evaluate",
			"conditionType": "Equals",
			"conditionValue": "2",
			"transition": "fd8d47b5-4188-4e4f-91e9-411aff7cc516"
		}, {
			"condition": "Evaluate",
			"conditionType": "Equals",
			"conditionValue": "3",
			"transition": "fd8d47b5-4188-4e4f-91e9-411aff7cc516"
		}, {
			"condition": "Evaluate",
			"conditionType": "Equals",
			"conditionValue": "4",
			"transition": "fd8d47b5-4188-4e4f-91e9-411aff7cc516"
		}, {
			"condition": "Evaluate",
			"conditionType": "Equals",
			"conditionValue": "5",
			"transition": "fd8d47b5-4188-4e4f-91e9-411aff7cc516"
		}, {
			"condition": "Evaluate",
			"conditionType": "Equals",
			"conditionValue": "6",
			"transition": "fd8d47b5-4188-4e4f-91e9-411aff7cc516"
		}, {
			"condition": "Evaluate",
			"conditionType": "Equals",
			"conditionValue": "7",
			"transition": "fd8d47b5-4188-4e4f-91e9-411aff7cc516"
		}, {
			"condition": "Evaluate",
			"conditionType": "Equals",
			"conditionValue": "8",
			"transition": "fd8d47b5-4188-4e4f-91e9-411aff7cc516"
		}, {
			"condition": "Evaluate",
			"conditionType": "Equals",
			"conditionValue": "9",
			"transition": "fd8d47b5-4188-4e4f-91e9-411aff7cc516"
		}],
		"parameters": [{
			"name": "Text",
			"value": "Please enter any key between 0 to 9 to listen to escalated incident message",
			"namespace": null
		}, {
			"name": "TextToSpeechType",
			"value": "text"
		}, {
			"name": "Timeout",
			"value": "5"
		}, {
			"name": "MaxDigits",
			"value": "1"
		}],
		"metadata": {
			"position": {
				"x": 486,
				"y": 311
			},
			"conditionMetadata": [{
				"id": "9a430b9d-4c78-45da-970a-e1030af789f5",
				"value": "0"
			}, {
				"id": "ab2aea0d-70d9-46ea-acc1-0e6b16783beb",
				"value": "1"
			}, {
				"id": "f1582c8b-75a7-4748-86ed-0bf28fbd24eb",
				"value": "2"
			}, {
				"id": "5b68bc88-72a1-4fe5-9bc2-5cf732abf29b",
				"value": "3"
			}, {
				"id": "7768e1bb-cbd1-41ae-ba96-82a93e7b1529",
				"value": "4"
			}, {
				"id": "3d25ea48-115d-42b7-800c-5b95dcd34e40",
				"value": "5"
			}, {
				"id": "2e6f57ed-46da-4a4d-a26b-a5a1d6ae97d9",
				"value": "6"
			}, {
				"id": "4c61ed8c-a59c-4dc6-a92c-96921858c1a7",
				"value": "7"
			}, {
				"id": "5389c7f0-c8f0-4461-9904-4c2490b0b7b0",
				"value": "8"
			}, {
				"id": "12d046b6-3a8f-4e8b-8547-b134a9a17b02",
				"value": "9"
			}],
			"useDynamic": false
		},
		"target": "Digits"
	}, {
		"id": "fd8d47b5-4188-4e4f-91e9-411aff7cc516",
		"type": "PlayPrompt",
		"branches": [{
			"condition": "Success",
			"transition": "35d29379-032f-47a1-bf95-f177ea3fd206"
		}],
		"parameters": [{
			"name": "Text",
			"value": "You have a new incident with message $.Attributes.message",
			"namespace": null
		}, {
			"name": "TextToSpeechType",
			"value": "text"
		}],
		"metadata": {
			"position": {
				"x": 815,
				"y": 364
			},
			"useDynamic": false
		}
	}, {
		"id": "a2ae63b0-e383-4a6f-a1af-21ab73cb9aa8",
		"type": "PlayPrompt",
		"branches": [{
			"condition": "Success",
			"transition": "7ef514f5-4447-4774-8432-446ad585c631"
		}],
		"parameters": [{
			"name": "AudioPrompt",
			"value": "arn:aws:connect:eu-central-1:746022503515:instance/736d65e0-6ce5-4210-9d44-55c366ea9a16/prompt/4e97b18a-f8ab-4d4c-b2d6-8f157a96b121",
			"namespace": null,
			"resourceName": "Beep.wav"
		}],
		"metadata": {
			"position": {
				"x": 231,
				"y": 685
			},
			"useDynamic": false,
			"promptName": "Beep.wav"
		}
	}],
	"version": "1",
	"type": "contactFlow",
	"start": "1b9f71dd-c18c-44c2-b772-36bbec4d7ec5",
	"metadata": {
		"entryPointPosition": {
			"x": 20,
			"y": 20
		},
		"snapToGrid": false,
		"name": "BMWOutboundCallFlow",
		"description": null,
		"type": "contactFlow",
		"status": "published",
		"hash": "a652bc059665b1cb2ec1ca98d85ddaa3b0f5e7e7b144f4a551d20fb65d576934"
	}
}